<?xml version="1.1" encoding="UTF-8"?>

<!--
 * See the NOTICE file distributed with this work for additional
 * information regarding copyright ownership.
 *
 * This is free software; you can redistribute it and/or modify it
 * under the terms of the GNU Lesser General Public License as
 * published by the Free Software Foundation; either version 2.1 of
 * the License, or (at your option) any later version.
 *
 * This software is distributed in the hope that it will be useful,
 * but WITHOUT ANY WARRANTY; without even the implied warranty of
 * MERCHANTABILITY or FITNESS FOR A PARTICULAR PURPOSE. See the GNU
 * Lesser General Public License for more details.
 *
 * You should have received a copy of the GNU Lesser General Public
 * License along with this software; if not, write to the Free
 * Software Foundation, Inc., 51 Franklin St, Fifth Floor, Boston, MA
 * 02110-1301 USA, or see the FSF site: http://www.fsf.org.
-->

<xwikidoc version="1.3" reference="Homework.Code.HomeworkTemplate" locale="">
  <web>Homework.Code</web>
  <name>HomeworkTemplate</name>
  <language/>
  <defaultLanguage/>
  <translation>0</translation>
  <creator>xwiki:XWiki.Admin</creator>
  <parent>Homework.Code.HomeworkClass</parent>
  <author>xwiki:XWiki.Admin</author>
  <contentAuthor>xwiki:XWiki.Admin</contentAuthor>
  <version>1.1</version>
  <title>HomeworkTemplate</title>
  <comment/>
  <minorEdit>false</minorEdit>
  <syntaxId>xwiki/2.1</syntaxId>
  <hidden>true</hidden>
  <content/>
  <object>
    <name>Homework.Code.HomeworkTemplate</name>
    <number>0</number>
    <className>Homework.Code.HomeworkClass</className>
    <guid>ffb35502-92d8-472c-9520-b4e7b6aead5b</guid>
    <class>
      <name>Homework.Code.HomeworkClass</name>
      <customClass/>
      <customMapping/>
      <defaultViewSheet/>
      <defaultEditSheet/>
      <defaultWeb/>
      <nameField/>
      <validationScript/>
      <course>
        <cache>0</cache>
        <classname>Structure.Code.CourseClass</classname>
        <customDisplay/>
        <defaultValue/>
        <disabled>0</disabled>
        <displayType>input</displayType>
        <freeText/>
        <hint/>
        <idField/>
        <multiSelect>0</multiSelect>
        <name>course</name>
        <number>6</number>
        <picker>1</picker>
        <prettyName>course</prettyName>
        <relationalStorage>0</relationalStorage>
        <separator> </separator>
        <separators/>
        <size>1</size>
        <sort/>
        <sql/>
        <unmodifiable>0</unmodifiable>
        <validationMessage/>
        <validationRegExp/>
        <valueField/>
        <classType>com.xpn.xwiki.objects.classes.PageClass</classType>
      </course>
      <deadline>
        <customDisplay/>
        <dateFormat>dd/MM/yyyy HH:mm:ss</dateFormat>
        <disabled>0</disabled>
        <emptyIsToday>1</emptyIsToday>
        <hint/>
        <name>deadline</name>
        <number>3</number>
        <picker>1</picker>
        <prettyName>deadline</prettyName>
        <size>20</size>
        <unmodifiable>0</unmodifiable>
        <validationMessage/>
        <validationRegExp/>
        <classType>com.xpn.xwiki.objects.classes.DateClass</classType>
      </deadline>
      <description>
        <contenttype/>
        <customDisplay/>
        <disabled>0</disabled>
        <editor/>
        <hint/>
        <name>description</name>
        <number>2</number>
        <picker>1</picker>
        <prettyName>description</prettyName>
        <rows>5</rows>
        <size>40</size>
        <unmodifiable>0</unmodifiable>
        <validationMessage/>
        <validationRegExp/>
        <classType>com.xpn.xwiki.objects.classes.TextAreaClass</classType>
      </description>
      <format>
        <cache>0</cache>
        <customDisplay/>
        <defaultValue/>
        <disabled>0</disabled>
        <displayType>checkbox</displayType>
        <freeText/>
        <hint/>
        <multiSelect>1</multiSelect>
        <name>format</name>
        <number>6</number>
        <picker>0</picker>
        <prettyName>format</prettyName>
        <relationalStorage>0</relationalStorage>
        <separator> </separator>
        <separators>|, </separators>
        <size>1</size>
        <sort/>
        <unmodifiable>0</unmodifiable>
        <validationMessage/>
        <validationRegExp/>
        <values>value1=JSON|value2=Zip|value3=PDF|value4=Tar</values>
        <classType>com.xpn.xwiki.objects.classes.StaticListClass</classType>
      </format>
      <groups>
        <cache>0</cache>
        <customDisplay/>
        <defaultValue/>
        <disabled>0</disabled>
        <displayType>select</displayType>
        <freeText/>
        <hint/>
        <multiSelect>1</multiSelect>
        <name>groups</name>
        <number>5</number>
        <picker>1</picker>
        <prettyName>groups</prettyName>
        <relationalStorage>0</relationalStorage>
        <separator> </separator>
        <separators/>
        <size>20</size>
        <sort/>
        <unmodifiable>0</unmodifiable>
        <usesList>0</usesList>
        <validationMessage/>
        <validationRegExp/>
        <classType>com.xpn.xwiki.objects.classes.GroupsClass</classType>
      </groups>
      <multipleAuthors>
        <customDisplay/>
        <defaultValue/>
        <disabled>0</disabled>
        <displayFormType>select</displayFormType>
        <displayType/>
        <hint/>
        <name>multipleAuthors</name>
        <number>7</number>
        <prettyName>multipleAuthors</prettyName>
        <unmodifiable>0</unmodifiable>
        <validationMessage/>
        <validationRegExp/>
        <classType>com.xpn.xwiki.objects.classes.BooleanClass</classType>
      </multipleAuthors>
      <professors>
        <cache>0</cache>
        <customDisplay/>
        <defaultValue/>
        <disabled>0</disabled>
        <displayType>input</displayType>
        <freeText/>
        <hint/>
        <multiSelect>1</multiSelect>
        <name>professors</name>
        <number>6</number>
        <picker>1</picker>
        <prettyName>professors</prettyName>
        <relationalStorage>0</relationalStorage>
        <separator> </separator>
        <separators/>
        <size>20</size>
        <sort/>
        <unmodifiable>0</unmodifiable>
        <usesList>0</usesList>
        <validationMessage/>
        <validationRegExp/>
        <classType>com.xpn.xwiki.objects.classes.UsersClass</classType>
      </professors>
    </class>
    <property>
      <course/>
    </property>
    <property>
      <deadline/>
    </property>
    <property>
      <description/>
    </property>
    <property>
      <format/>
    </property>
    <property>
      <groups/>
    </property>
    <property>
      <multipleAuthors/>
    </property>
    <property>
      <professors/>
    </property>
  </object>
</xwikidoc>
